{
	"info": {
		"_postman_id": "6e806576-3abf-4eaf-a639-5cc882c6161f",
		"name": "10-E-Commerce-API",
		"schema": "https://schema.getpostman.com/json/collection/v2.1.0/collection.json",
		"_exporter_id": "27755277",
		"_collection_link": "https://galactic-meteor-248247.postman.co/workspace/Curso-node~8b875c4d-0f4d-4332-9cb4-fb1ea1f8fba6/collection/27755277-6e806576-3abf-4eaf-a639-5cc882c6161f?action=share&creator=27755277&source=collection_link"
	},
	"item": [
		{
			"name": "Auth",
			"item": [
				{
					"name": "Logout User",
					"request": {
						"method": "GET",
						"header": [],
						"url": {
							"raw": "{{URL}}/auth/logout",
							"host": [
								"{{URL}}"
							],
							"path": [
								"auth",
								"logout"
							]
						}
					},
					"response": []
				},
				{
					"name": "Login User",
					"request": {
						"method": "POST",
						"header": [],
						"body": {
							"mode": "raw",
							"raw": "{\r\n    \"email\": \"jean8@gmail.com\",\r\n    \"password\": \"secret\"\r\n}",
							"options": {
								"raw": {
									"language": "json"
								}
							}
						},
						"url": {
							"raw": "{{URL}}/auth/login",
							"host": [
								"{{URL}}"
							],
							"path": [
								"auth",
								"login"
							]
						}
					},
					"response": []
				},
				{
					"name": "Register User",
					"request": {
						"method": "POST",
						"header": [],
						"body": {
							"mode": "raw",
							"raw": "{\r\n    \"name\": \"jean\",\r\n    \"email\": \"jean8@gmail.com\",\r\n    \"password\": \"secret\"\r\n}",
							"options": {
								"raw": {
									"language": "json"
								}
							}
						},
						"url": {
							"raw": "{{URL}}/auth/register",
							"host": [
								"{{URL}}"
							],
							"path": [
								"auth",
								"register"
							]
						}
					},
					"response": []
				}
			]
		},
		{
			"name": "User",
			"item": [
				{
					"name": "Get All users",
					"request": {
						"method": "GET",
						"header": [],
						"url": {
							"raw": "{{URL}}/users",
							"host": [
								"{{URL}}"
							],
							"path": [
								"users"
							]
						}
					},
					"response": []
				},
				{
					"name": "Get Single user",
					"request": {
						"method": "GET",
						"header": [],
						"url": {
							"raw": "{{URL}}/user/123",
							"host": [
								"{{URL}}"
							],
							"path": [
								"user",
								"123"
							]
						}
					},
					"response": []
				},
				{
					"name": "Show Current User",
					"request": {
						"method": "GET",
						"header": [],
						"url": {
							"raw": "{{URL}}/users/showMe",
							"host": [
								"{{URL}}"
							],
							"path": [
								"users",
								"showMe"
							]
						}
					},
					"response": []
				},
				{
					"name": "Update User",
					"request": {
						"method": "POST",
						"header": [],
						"url": {
							"raw": "{{URL}}/user/updateUser",
							"host": [
								"{{URL}}"
							],
							"path": [
								"user",
								"updateUser"
							]
						}
					},
					"response": []
				},
				{
					"name": "Update User Password",
					"request": {
						"method": "POST",
						"header": [],
						"url": {
							"raw": "{{URL}}/user/updateUserPassword",
							"host": [
								"{{URL}}"
							],
							"path": [
								"user",
								"updateUserPassword"
							]
						}
					},
					"response": []
				}
			]
		}
	]
}